progfiguration/__init__.py
progfiguration/age.py
progfiguration/cmd.py
progfiguration/progfigtypes.py
progfiguration/ssh.py
progfiguration/version.py
progfiguration/cli/__init__.py
progfiguration/cli/progfiguration_cmd.py
progfiguration/example_site/__init__.py
progfiguration/example_site/inventory.yml
progfiguration/example_site/readme.md
progfiguration/example_site/groups/__init__.py
progfiguration/example_site/groups/group1.py
progfiguration/example_site/groups/universal.py
progfiguration/example_site/nodes/__init__.py
progfiguration/example_site/nodes/node1.py
progfiguration/example_site/roles/__init__.py
progfiguration/example_site/roles/settz.py
progfiguration/example_site/sitelib/__init__.py
progfiguration/inventory/__init__.py
progfiguration/inventory/nodes.py
progfiguration/inventory/roles.py
progfiguration/localhost/__init__.py
progfiguration/localhost/authorized_keys.py
progfiguration/localhost/disks.py
progfiguration/localhost/localusers.py
progfiguration/remotebrute/__init__.py
progfiguration/remoting/__init__.py
progfiguration/remoting/rfuncs.py
progfiguration/sitewrapper/__init__.py
progfiguration/temple/__init__.py
progfiguration-0.0.1.dist-info/METADATA
progfiguration-0.0.1.dist-info/WHEEL
progfiguration-0.0.1.dist-info/entry_points.txt
progfiguration-0.0.1.dist-info/top_level.txt
progfiguration-0.0.1.dist-info/RECORD
