Metadata-Version: 2.1
Name: progfiguration
Version: 0.0.1
Summary: PROGramatic conFIGURATION for your infrastructure
Author-email: Micah R Ledbetter <me@micahrl.com>
License: MIT
Project-URL: Homepage, https://github.com/mrled/progfiguration
Requires-Python: >=3.8
Requires-Dist: PyYAML
Requires-Dist: pytz
Requires-Dist: requests
Provides-Extra: development
Requires-Dist: black ; extra == 'development'
Requires-Dist: build ; extra == 'development'
Requires-Dist: mypy ; extra == 'development'
Requires-Dist: twine ; extra == 'development'
Provides-Extra: ssh
Requires-Dist: mitogen ; extra == 'ssh'
